{"on": [{"within": {"@id": "https://ericayhayes.github.io/audubon/img/derivatives/fifty_birdsofamerica_manifest.json", "@type": "sc:Manifest"}, "full": "https://ericayhayes.github.io/audubon/img/derivatives/iiif/images/obj30/info.json", "@type": "oa:SpecificResource", "selector": {"default": {"@type": "oa:FragmentSelector", "value": "xywh=1145,3278,269,23"}, "item": {"@type": "oa:SvgSelector", "value": "<svg xmlns='http://www.w3.org/2000/svg'><path xmlns=\"http://www.w3.org/2000/svg\" d=\"M1145.2138,3300.56858h134.63636v0h134.63636v-11.27273v-11.27273h-134.63636h-134.63636v11.27273z\" data-paper-data=\"{&quot;strokeWidth&quot;:1,&quot;rotation&quot;:0,&quot;deleteIcon&quot;:null,&quot;rotationIcon&quot;:null,&quot;group&quot;:null,&quot;editable&quot;:true,&quot;annotation&quot;:null}\" id=\"rectangle_36aabd6f-ac95-4935-b169-166d3488d856\" fill-opacity=\"0\" fill=\"#00bfff\" fill-rule=\"nonzero\" stroke=\"#00bfff\" stroke-width=\"1\" stroke-linecap=\"butt\" stroke-linejoin=\"miter\" stroke-miterlimit=\"10\" stroke-dasharray=\"\" stroke-dashoffset=\"0\" font-family=\"none\" font-weight=\"none\" font-size=\"none\" text-anchor=\"none\" style=\"mix-blend-mode: normal\"/></svg>"}, "@type": "oa:Choice"}}], "motivation": ["oa:commenting"], "resource": [{"chars": "<p>Male adult Spring plummage</p>", "@type": "dctypes:Text", "format": "text/html"}], "oa:annotatedBy": [null], "@context": "http://iiif.io/api/presentation/2/context.json", "@id": "/annotate/annotations/467bf356-8749-11ea-9b41-5254008afee6.json", "@type": "oa:Annotation", "oa:annotatedAt": "2020-04-25T23:05:37.194Z"}